setup.py
gnarlytvdb/__init__.py
gnarlytvdb/util.py
gnarlytvdb.egg-info/PKG-INFO
gnarlytvdb.egg-info/SOURCES.txt
gnarlytvdb.egg-info/dependency_links.txt
gnarlytvdb.egg-info/requires.txt
gnarlytvdb.egg-info/top_level.txt