Metadata-Version: 1.0
Name: gnarlytvdb
Version: 0.6
Summary: A python interface to thetvdb.com xml api.
Home-page: https://github.com/steinitzu/gnarly-tvdb
Author: Steinthor Palsson
Author-email: steinitzu@gmail.com
License: MIT
Platform: UNKNOWN
